[{"pk": 7, "model": "conf.resultstring", "fields": {"indicates": "pos", "match_type": "istartswith", "applies_to_all": false, "value": "confirm"}}, {"pk": 5, "model": "conf.resultstring", "fields": {"indicates": "pos", "match_type": "istartswith", "applies_to_all": true, "value": "detec"}}, {"pk": 3, "model": "conf.resultstring", "fields": {"indicates": "ind", "match_type": "istartswith", "applies_to_all": true, "value": "indeterminate"}}, {"pk": 2, "model": "conf.resultstring", "fields": {"indicates": "neg", "match_type": "istartswith", "applies_to_all": true, "value": "neg"}}, {"pk": 8, "model": "conf.resultstring", "fields": {"indicates": "neg", "match_type": "istartswith", "applies_to_all": true, "value": "non"}}, {"pk": 9, "model": "conf.resultstring", "fields": {"indicates": "neg", "match_type": "istartswith", "applies_to_all": true, "value": "not det"}}, {"pk": 11, "model": "conf.resultstring", "fields": {"indicates": "ind", "match_type": "istartswith", "applies_to_all": true, "value": "not done"}}, {"pk": 10, "model": "conf.resultstring", "fields": {"indicates": "neg", "match_type": "istartswith", "applies_to_all": true, "value": "nr"}}, {"pk": 4, "model": "conf.resultstring", "fields": {"indicates": "pos", "match_type": "istartswith", "applies_to_all": true, "value": "pos"}}, {"pk": 6, "model": "conf.resultstring", "fields": {"indicates": "pos", "match_type": "istartswith", "applies_to_all": true, "value": "reactiv"}}, {"pk": 12, "model": "conf.resultstring", "fields": {"indicates": "ind", "match_type": "istartswith", "applies_to_all": true, "value": "tnp"}}]